<?xml version="1.0" ?>
<scene camera="0,1,-10,0,0,0" template="..\Templates\master.xml">
	<Shot enabled="False" end="8.0" name="05" preroll="0.0" scene="05" speed="1.0" start="0.0">
		<Channel mode="hermite" name="uOrigin.x">0.0,0.0,0.0,0.0,8.0,0.0430655336651,0,2,8.0,0.0430655336651,8.0,0.0430655336651,0.0,0.0,0,2</Channel>
		<Channel mode="hermite" name="uOrigin.y">0.0,0.0,0.0,3.0,8.0,7.3284202729,0,2,8.0,7.3284202729,8.0,10.3284202729,0.0,0.0,0,2</Channel>
		<Channel mode="hermite" name="uOrigin.z">0.0,0.0,0.0,-40.0,8.0,3.0307495551,0,2,8.0,3.0307495551,8.0,-36.9692504449,0.0,0.0,0,2</Channel>
		<Channel mode="hermite" name="uAngles.x">0.0,0.0,0.0,0.0,8.0,-0.239467849224,0,2,8.0,-0.239467849224,8.0,-0.239467849224,0.0,0.0,0,2</Channel>
		<Channel mode="hermite" name="uAngles.y">0.0,0.0,0.0,0.0,8.0,-0.0133037694013,0,2,8.0,-0.0133037694013,8.0,-0.0133037694013,0.0,0.0,0,2</Channel>
		<Channel mode="hermite" name="uAngles.z">0.0,0.0,0.0,0.0,8.0,0.0,0,2,8.0,-0.0,8.0,0.0,0.0,0.0,0,2</Channel>
		<Channel mode="hermite" name="uFovBias">0.0,0.0,0.0,0.15,0.0,0.0,0,2</Channel>
		<Channel mode="hermite" name="uBloom">0.0,0.0,0.0,0.01,0.0,0.0,0,2</Channel>
		<Channel mode="hermite" name="uLensDirt"/>
		<Channel mode="hermite" name="uFishEye">0.0,0.0,0.0,0.0,0.0,0.0,0,2</Channel>
		<Channel mode="hermite" name="uChromaticAberrationRadius">0.0,0.0,0.0,0.0,0.0,0.0,0,2</Channel>
		<Channel mode="hermite" name="uVignette">0.0,0.0,0.0,0.0,0.0,0.0,0,2</Channel>
		<Channel mode="hermite" name="uTimer">0.0,0.0,0.0,0.0,8.0,4.0,0,2,8.0,4.0,8.0,4.0,0.0,0.0,0,2</Channel>
	</Shot>
	<Shot enabled="False" end="1.0" name="cover" preroll="0.0" scene="05" speed="1.0" start="0.0">
		<Channel mode="hermite" name="uOrigin.x">0.0,0.0,0.0,0.00985659136041,0.0,0.0,0,0</Channel>
		<Channel mode="hermite" name="uOrigin.y">0.0,0.0,0.0,3.61539645777,0.0,0.0,0,0</Channel>
		<Channel mode="hermite" name="uOrigin.z">0.0,0.0,0.0,-39.3738202021,0.0,0.0,0,0</Channel>
		<Channel mode="hermite" name="uAngles.x">0.0,0.0,0.0,-0.05,0.0,0.0,0,0</Channel>
		<Channel mode="hermite" name="uAngles.y">0.0,0.0,0.0,-0.00299334811529,0.0,0.0,0,0</Channel>
		<Channel mode="hermite" name="uAngles.z">0.0,0.0,0.0,0.0,0.0,0.0,0,0</Channel>
		<Channel mode="hermite" name="uFovBias">0.0,0.0,0.0,0.18,0.0,0.0,0,2</Channel>
		<Channel mode="hermite" name="uBloom">0.0,0.0,0.0,0.01,0.0,0.0,0,2</Channel>
		<Channel mode="hermite" name="uLensDirt">0.0,0.0,0.0,0.04,1.0,0.0,0,2</Channel>
		<Channel mode="hermite" name="uFishEye">0.0,0.0,0.0,0.0,1.0,1.0,0,2</Channel>
		<Channel mode="hermite" name="uChromaticAberrationRadius">0.0,0.0,0.0,0.0,0.0,0.0,0,3</Channel>
		<Channel mode="hermite" name="uVignette">0.0,0.0,0.0,0.0,0.0,0.0,0,2</Channel>
		<Channel mode="hermite" name="uTimer">0.0,0.0,0.0,0.9,0.0,0.0,0,0</Channel>
	</Shot>
</scene>